{
  "config": {
    "initialCapital": 1000,
    "startDate": "2026-02-08T15:03:44.226Z",
    "endDate": "2026-02-15T15:03:44.226Z",
    "minArbitrageGap": 0.015
  },
  "options": {
    "days": 7,
    "scenario": "RANDOM",
    "markets": 5,
    "output": "./reports/backtest-7days.json"
  },
  "result": {
    "totalTrades": 45,
    "winningTrades": 45,
    "losingTrades": 0,
    "winRate": 100,
    "totalPnL": 512.5262803556809,
    "totalPnLPercent": 51.252628035568094,
    "avgReturn": 5.694736448396455,
    "maxDrawdown": 7.161143410389574,
    "sharpeRatio": 2.9099218815277967,
    "trades": [
      {
        "id": 1,
        "signalId": 1,
        "marketId": "market-1",
        "marketName": "Test Market 1",
        "side": "NO",
        "entryPrice": 0.4753,
        "entryDeviation": 0.04820000000000002,
        "amount": 200,
        "quantity": 420.78687144961077,
        "entryTime": "2026-02-15T15:03:44.230Z",
        "status": "CLOSED",
        "exitPrice": 0.4967,
        "exitTime": "2026-02-08T15:18:44.219Z",
        "exitReason": "PARTIAL_CLOSE",
        "pnl": 9.00483904902166,
        "pnlPercent": 4.50241952451083
      },
      {
        "id": 2,
        "signalId": 2,
        "marketId": "market-3",
        "marketName": "Test Market 3",
        "side": "YES",
        "entryPrice": 0.4577,
        "entryDeviation": 0.07600000000000007,
        "amount": 200,
        "quantity": 436.9674459252786,
        "entryTime": "2026-02-15T15:03:44.230Z",
        "status": "CLOSED",
        "exitPrice": 0.5025,
        "exitTime": "2026-02-08T15:18:44.222Z",
        "exitReason": "PARTIAL_CLOSE",
        "pnl": 19.57614157745246,
        "pnlPercent": 9.78807078872623
      },
      {
        "id": 3,
        "signalId": 3,
        "marketId": "market-5",
        "marketName": "Test Market 5",
        "side": "YES",
        "entryPrice": 0.4723,
        "entryDeviation": 0.04959999999999998,
        "amount": 200,
        "quantity": 423.4596654668643,
        "entryTime": "2026-02-15T15:03:44.230Z",
        "status": "CLOSED",
        "exitPrice": 0.4972,
        "exitTime": "2026-02-08T15:33:44.224Z",
        "exitReason": "PARTIAL_CLOSE",
        "pnl": 10.544145670124912,
        "pnlPercent": 5.272072835062456
      },
      {
        "id": 4,
        "signalId": 4,
        "marketId": "market-4",
        "marketName": "Test Market 4",
        "side": "NO",
        "entryPrice": 0.486,
        "entryDeviation": 0.025600000000000067,
        "amount": 200,
        "quantity": 411.52263374485597,
        "entryTime": "2026-02-15T15:03:44.230Z",
        "status": "CLOSED",
        "exitPrice": 0.4973,
        "exitTime": "2026-02-08T15:28:44.223Z",
        "exitReason": "PARTIAL_CLOSE",
        "pnl": 4.650205761316886,
        "pnlPercent": 2.325102880658443
      },
      {
        "id": 5,
        "signalId": 5,
        "marketId": "market-5",
        "marketName": "Test Market 5",
        "side": "NO",
        "entryPrice": 0.4692,
        "entryDeviation": 0.056599999999999984,
        "amount": 200,
        "quantity": 426.25745950554136,
        "entryTime": "2026-02-15T15:03:44.230Z",
        "status": "CLOSED",
        "exitPrice": 0.5007,
        "exitTime": "2026-02-08T15:33:44.224Z",
        "exitReason": "PARTIAL_CLOSE",
        "pnl": 13.427109974424566,
        "pnlPercent": 6.713554987212284
      },
      {
        "id": 6,
        "signalId": 6,
        "marketId": "market-3",
        "marketName": "Test Market 3",
        "side": "YES",
        "entryPrice": 0.4595,
        "entryDeviation": 0.07799999999999996,
        "amount": 200,
        "quantity": 435.25571273122955,
        "entryTime": "2026-02-15T15:03:44.230Z",
        "status": "CLOSED",
        "exitPrice": 0.4997,
        "exitTime": "2026-02-08T15:33:44.222Z",
        "exitReason": "PARTIAL_CLOSE",
        "pnl": 17.49727965179541,
        "pnlPercent": 8.748639825897705
      },
      {
        "id": 7,
        "signalId": 7,
        "marketId": "market-4",
        "marketName": "Test Market 4",
        "side": "NO",
        "entryPrice": 0.4744,
        "entryDeviation": 0.050899999999999945,
        "amount": 200,
        "quantity": 421.5851602023609,
        "entryTime": "2026-02-15T15:03:44.231Z",
        "status": "CLOSED",
        "exitPrice": 0.4973,
        "exitTime": "2026-02-08T15:28:44.223Z",
        "exitReason": "PARTIAL_CLOSE",
        "pnl": 9.654300168634078,
        "pnlPercent": 4.827150084317039
      },
      {
        "id": 8,
        "signalId": 8,
        "marketId": "market-5",
        "marketName": "Test Market 5",
        "side": "NO",
        "entryPrice": 0.4662,
        "entryDeviation": 0.06319999999999992,
        "amount": 200,
        "quantity": 429.000429000429,
        "entryTime": "2026-02-15T15:03:44.231Z",
        "status": "CLOSED",
        "exitPrice": 0.5007,
        "exitTime": "2026-02-08T15:33:44.224Z",
        "exitReason": "PARTIAL_CLOSE",
        "pnl": 14.800514800514813,
        "pnlPercent": 7.400257400257407
      },
      {
        "id": 9,
        "signalId": 9,
        "marketId": "market-1",
        "marketName": "Test Market 1",
        "side": "NO",
        "entryPrice": 0.4779,
        "entryDeviation": 0.03639999999999999,
        "amount": 200,
        "quantity": 418.4975936388366,
        "entryTime": "2026-02-15T15:03:44.231Z",
        "status": "CLOSED",
        "exitPrice": 0.4987,
        "exitTime": "2026-02-08T15:38:44.219Z",
        "exitReason": "PARTIAL_CLOSE",
        "pnl": 8.704749947687795,
        "pnlPercent": 4.352374973843897
      },
      {
        "id": 10,
        "signalId": 10,
        "marketId": "market-2",
        "marketName": "Test Market 2",
        "side": "NO",
        "entryPrice": 0.4739,
        "entryDeviation": 0.050799999999999956,
        "amount": 200,
        "quantity": 422.02996412745307,
        "entryTime": "2026-02-15T15:03:44.231Z",
        "status": "CLOSED",
        "exitPrice": 0.5039,
        "exitTime": "2026-02-08T15:33:44.221Z",
        "exitReason": "PARTIAL_CLOSE",
        "pnl": 12.660898923823604,
        "pnlPercent": 6.330449461911803
      },
      {
        "id": 11,
        "signalId": 11,
        "marketId": "market-3",
        "marketName": "Test Market 3",
        "side": "YES",
        "entryPrice": 0.4725,
        "entryDeviation": 0.05449999999999999,
        "amount": 200,
        "quantity": 423.2804232804233,
        "entryTime": "2026-02-15T15:03:44.231Z",
        "status": "CLOSED",
        "exitPrice": 0.4997,
        "exitTime": "2026-02-08T15:33:44.222Z",
        "exitReason": "PARTIAL_CLOSE",
        "pnl": 11.513227513227514,
        "pnlPercent": 5.756613756613757
      },
      {
        "id": 12,
        "signalId": 12,
        "marketId": "market-5",
        "marketName": "Test Market 5",
        "side": "NO",
        "entryPrice": 0.4688,
        "entryDeviation": 0.06010000000000004,
        "amount": 200,
        "quantity": 426.6211604095563,
        "entryTime": "2026-02-15T15:03:44.233Z",
        "status": "CLOSED",
        "exitPrice": 0.5038,
        "exitTime": "2026-02-09T00:08:44.224Z",
        "exitReason": "PARTIAL_CLOSE",
        "pnl": 14.931740614334483,
        "pnlPercent": 7.465870307167241
      },
      {
        "id": 13,
        "signalId": 13,
        "marketId": "market-3",
        "marketName": "Test Market 3",
        "side": "YES",
        "entryPrice": 0.4686,
        "entryDeviation": 0.06129999999999991,
        "amount": 200,
        "quantity": 426.8032437046521,
        "entryTime": "2026-02-15T15:03:44.233Z",
        "status": "CLOSED",
        "exitPrice": 0.5004,
        "exitTime": "2026-02-09T00:13:44.222Z",
        "exitReason": "PARTIAL_CLOSE",
        "pnl": 13.572343149807912,
        "pnlPercent": 6.786171574903956
      },
      {
        "id": 14,
        "signalId": 14,
        "marketId": "market-1",
        "marketName": "Test Market 1",
        "side": "NO",
        "entryPrice": 0.4784,
        "entryDeviation": 0.03839999999999999,
        "amount": 200,
        "quantity": 418.0602006688963,
        "entryTime": "2026-02-15T15:03:44.234Z",
        "status": "CLOSED",
        "exitPrice": 0.4974,
        "exitTime": "2026-02-09T00:18:44.219Z",
        "exitReason": "PARTIAL_CLOSE",
        "pnl": 7.943143812709037,
        "pnlPercent": 3.9715719063545185
      },
      {
        "id": 15,
        "signalId": 15,
        "marketId": "market-5",
        "marketName": "Test Market 5",
        "side": "NO",
        "entryPrice": 0.4752,
        "entryDeviation": 0.045599999999999974,
        "amount": 200,
        "quantity": 420.87542087542084,
        "entryTime": "2026-02-15T15:03:44.234Z",
        "status": "CLOSED",
        "exitPrice": 0.5012,
        "exitTime": "2026-02-09T00:18:44.224Z",
        "exitReason": "PARTIAL_CLOSE",
        "pnl": 10.942760942760929,
        "pnlPercent": 5.471380471380464
      },
      {
        "id": 16,
        "signalId": 16,
        "marketId": "market-3",
        "marketName": "Test Market 3",
        "side": "NO",
        "entryPrice": 0.4796,
        "entryDeviation": 0.03649999999999998,
        "amount": 200,
        "quantity": 417.01417848206836,
        "entryTime": "2026-02-15T15:03:44.237Z",
        "status": "CLOSED",
        "exitPrice": 0.4989,
        "exitTime": "2026-02-10T00:13:44.222Z",
        "exitReason": "PARTIAL_CLOSE",
        "pnl": 8.048373644703913,
        "pnlPercent": 4.024186822351957
      },
      {
        "id": 17,
        "signalId": 17,
        "marketId": "market-1",
        "marketName": "Test Market 1",
        "side": "NO",
        "entryPrice": 0.4697,
        "entryDeviation": 0.05390000000000006,
        "amount": 200,
        "quantity": 425.8037044922291,
        "entryTime": "2026-02-15T15:03:44.237Z",
        "status": "CLOSED",
        "exitPrice": 0.4958,
        "exitTime": "2026-02-10T00:13:44.219Z",
        "exitReason": "PARTIAL_CLOSE",
        "pnl": 11.113476687247184,
        "pnlPercent": 5.556738343623592
      },
      {
        "id": 18,
        "signalId": 18,
        "marketId": "market-2",
        "marketName": "Test Market 2",
        "side": "YES",
        "entryPrice": 0.4856,
        "entryDeviation": 0.026900000000000035,
        "amount": 200,
        "quantity": 411.8616144975289,
        "entryTime": "2026-02-15T15:03:44.237Z",
        "status": "CLOSED",
        "exitPrice": 0.5018,
        "exitTime": "2026-02-10T00:13:44.221Z",
        "exitReason": "PARTIAL_CLOSE",
        "pnl": 6.6721581548599875,
        "pnlPercent": 3.3360790774299938
      },
      {
        "id": 19,
        "signalId": 19,
        "marketId": "market-3",
        "marketName": "Test Market 3",
        "side": "NO",
        "entryPrice": 0.4692,
        "entryDeviation": 0.05580000000000007,
        "amount": 200,
        "quantity": 426.25745950554136,
        "entryTime": "2026-02-15T15:03:44.237Z",
        "status": "CLOSED",
        "exitPrice": 0.4989,
        "exitTime": "2026-02-10T00:13:44.222Z",
        "exitReason": "PARTIAL_CLOSE",
        "pnl": 12.65984654731458,
        "pnlPercent": 6.32992327365729
      },
      {
        "id": 20,
        "signalId": 20,
        "marketId": "market-4",
        "marketName": "Test Market 4",
        "side": "YES",
        "entryPrice": 0.4704,
        "entryDeviation": 0.05479999999999996,
        "amount": 200,
        "quantity": 425.1700680272109,
        "entryTime": "2026-02-15T15:03:44.237Z",
        "status": "CLOSED",
        "exitPrice": 0.4891,
        "exitTime": "2026-02-10T00:13:44.223Z",
        "exitReason": "PARTIAL_CLOSE",
        "pnl": 7.950680272108841,
        "pnlPercent": 3.9753401360544207
      },
      {
        "id": 21,
        "signalId": 21,
        "marketId": "market-5",
        "marketName": "Test Market 5",
        "side": "YES",
        "entryPrice": 0.4789,
        "entryDeviation": 0.03839999999999999,
        "amount": 200,
        "quantity": 417.62372102735435,
        "entryTime": "2026-02-15T15:03:44.240Z",
        "status": "CLOSED",
        "exitPrice": 0.5023,
        "exitTime": "2026-02-11T00:18:44.224Z",
        "exitReason": "PARTIAL_CLOSE",
        "pnl": 9.772395072040082,
        "pnlPercent": 4.886197536020041
      },
      {
        "id": 22,
        "signalId": 22,
        "marketId": "market-5",
        "marketName": "Test Market 5",
        "side": "NO",
        "entryPrice": 0.4688,
        "entryDeviation": 0.06099999999999994,
        "amount": 200,
        "quantity": 426.6211604095563,
        "entryTime": "2026-02-15T15:03:44.240Z",
        "status": "CLOSED",
        "exitPrice": 0.4984,
        "exitTime": "2026-02-11T00:18:44.224Z",
        "exitReason": "PARTIAL_CLOSE",
        "pnl": 12.627986348122873,
        "pnlPercent": 6.3139931740614355
      },
      {
        "id": 23,
        "signalId": 23,
        "marketId": "market-2",
        "marketName": "Test Market 2",
        "side": "NO",
        "entryPrice": 0.4706,
        "entryDeviation": 0.05499999999999994,
        "amount": 200,
        "quantity": 424.9893752656183,
        "entryTime": "2026-02-15T15:03:44.240Z",
        "status": "CLOSED",
        "exitPrice": 0.4964,
        "exitTime": "2026-02-11T00:18:44.221Z",
        "exitReason": "PARTIAL_CLOSE",
        "pnl": 10.964725881852948,
        "pnlPercent": 5.482362940926474
      },
      {
        "id": 24,
        "signalId": 24,
        "marketId": "market-5",
        "marketName": "Test Market 5",
        "side": "YES",
        "entryPrice": 0.4671,
        "entryDeviation": 0.061799999999999966,
        "amount": 200,
        "quantity": 428.17383857846283,
        "entryTime": "2026-02-15T15:03:44.241Z",
        "status": "CLOSED",
        "exitPrice": 0.5023,
        "exitTime": "2026-02-11T00:18:44.224Z",
        "exitReason": "PARTIAL_CLOSE",
        "pnl": 15.071719117961871,
        "pnlPercent": 7.535859558980936
      },
      {
        "id": 25,
        "signalId": 25,
        "marketId": "market-3",
        "marketName": "Test Market 3",
        "side": "YES",
        "entryPrice": 0.4558,
        "entryDeviation": 0.08109999999999995,
        "amount": 200,
        "quantity": 438.7889425186485,
        "entryTime": "2026-02-15T15:03:44.243Z",
        "status": "CLOSED",
        "exitPrice": 0.4996,
        "exitTime": "2026-02-12T00:08:44.222Z",
        "exitReason": "PARTIAL_CLOSE",
        "pnl": 19.218955682316807,
        "pnlPercent": 9.609477841158403
      },
      {
        "id": 26,
        "signalId": 26,
        "marketId": "market-4",
        "marketName": "Test Market 4",
        "side": "YES",
        "entryPrice": 0.4716,
        "entryDeviation": 0.0494,
        "amount": 200,
        "quantity": 424.0882103477523,
        "entryTime": "2026-02-15T15:03:44.243Z",
        "status": "CLOSED",
        "exitPrice": 0.4955,
        "exitTime": "2026-02-12T00:08:44.223Z",
        "exitReason": "PARTIAL_CLOSE",
        "pnl": 10.13570822731127,
        "pnlPercent": 5.067854113655635
      },
      {
        "id": 27,
        "signalId": 27,
        "marketId": "market-2",
        "marketName": "Test Market 2",
        "side": "NO",
        "entryPrice": 0.4658,
        "entryDeviation": 0.06769999999999998,
        "amount": 200,
        "quantity": 429.36882782310005,
        "entryTime": "2026-02-15T15:03:44.243Z",
        "status": "CLOSED",
        "exitPrice": 0.5017,
        "exitTime": "2026-02-12T00:23:44.221Z",
        "exitReason": "PARTIAL_CLOSE",
        "pnl": 15.41434091884931,
        "pnlPercent": 7.707170459424656
      },
      {
        "id": 28,
        "signalId": 28,
        "marketId": "market-2",
        "marketName": "Test Market 2",
        "side": "NO",
        "entryPrice": 0.4731,
        "entryDeviation": 0.04679999999999995,
        "amount": 200,
        "quantity": 422.7436060029592,
        "entryTime": "2026-02-15T15:03:44.243Z",
        "status": "CLOSED",
        "exitPrice": 0.5017,
        "exitTime": "2026-02-12T00:23:44.221Z",
        "exitReason": "PARTIAL_CLOSE",
        "pnl": 12.090467131684639,
        "pnlPercent": 6.045233565842319
      },
      {
        "id": 29,
        "signalId": 29,
        "marketId": "market-5",
        "marketName": "Test Market 5",
        "side": "NO",
        "entryPrice": 0.4753,
        "entryDeviation": 0.04170000000000007,
        "amount": 200,
        "quantity": 420.78687144961077,
        "entryTime": "2026-02-15T15:03:44.243Z",
        "status": "CLOSED",
        "exitPrice": 0.4978,
        "exitTime": "2026-02-12T00:33:44.224Z",
        "exitReason": "PARTIAL_CLOSE",
        "pnl": 9.46770460761625,
        "pnlPercent": 4.733852303808125
      },
      {
        "id": 30,
        "signalId": 30,
        "marketId": "market-1",
        "marketName": "Test Market 1",
        "side": "NO",
        "entryPrice": 0.464,
        "entryDeviation": 0.06359999999999999,
        "amount": 200,
        "quantity": 431.03448275862064,
        "entryTime": "2026-02-15T15:03:44.243Z",
        "status": "CLOSED",
        "exitPrice": 0.4974,
        "exitTime": "2026-02-12T00:28:44.219Z",
        "exitReason": "PARTIAL_CLOSE",
        "pnl": 14.396551724137924,
        "pnlPercent": 7.198275862068962
      },
      {
        "id": 31,
        "signalId": 31,
        "marketId": "market-1",
        "marketName": "Test Market 1",
        "side": "NO",
        "entryPrice": 0.4635,
        "entryDeviation": 0.07079999999999997,
        "amount": 200,
        "quantity": 431.4994606256742,
        "entryTime": "2026-02-15T15:03:44.246Z",
        "status": "CLOSED",
        "exitPrice": 0.4886,
        "exitTime": "2026-02-13T00:08:44.219Z",
        "exitReason": "PARTIAL_CLOSE",
        "pnl": 10.830636461704403,
        "pnlPercent": 5.415318230852201
      },
      {
        "id": 32,
        "signalId": 32,
        "marketId": "market-4",
        "marketName": "Test Market 4",
        "side": "YES",
        "entryPrice": 0.4846,
        "entryDeviation": 0.029400000000000093,
        "amount": 200,
        "quantity": 412.71151465125877,
        "entryTime": "2026-02-15T15:03:44.246Z",
        "status": "CLOSED",
        "exitPrice": 0.4985,
        "exitTime": "2026-02-13T00:13:44.223Z",
        "exitReason": "PARTIAL_CLOSE",
        "pnl": 5.736690053652507,
        "pnlPercent": 2.8683450268262534
      },
      {
        "id": 33,
        "signalId": 33,
        "marketId": "market-5",
        "marketName": "Test Market 5",
        "side": "NO",
        "entryPrice": 0.4855,
        "entryDeviation": 0.02510000000000001,
        "amount": 200,
        "quantity": 411.946446961895,
        "entryTime": "2026-02-15T15:03:44.246Z",
        "status": "CLOSED",
        "exitPrice": 0.5031,
        "exitTime": "2026-02-13T00:18:44.224Z",
        "exitReason": "PARTIAL_CLOSE",
        "pnl": 7.250257466529353,
        "pnlPercent": 3.6251287332646767
      },
      {
        "id": 34,
        "signalId": 34,
        "marketId": "market-2",
        "marketName": "Test Market 2",
        "side": "NO",
        "entryPrice": 0.4859,
        "entryDeviation": 0.026799999999999935,
        "amount": 200,
        "quantity": 411.6073266104137,
        "entryTime": "2026-02-15T15:03:44.246Z",
        "status": "CLOSED",
        "exitPrice": 0.4954,
        "exitTime": "2026-02-13T00:13:44.221Z",
        "exitReason": "PARTIAL_CLOSE",
        "pnl": 3.9102696027989334,
        "pnlPercent": 1.9551348013994667
      },
      {
        "id": 35,
        "signalId": 35,
        "marketId": "market-4",
        "marketName": "Test Market 4",
        "side": "NO",
        "entryPrice": 0.4614,
        "entryDeviation": 0.07580000000000009,
        "amount": 200,
        "quantity": 433.4633723450369,
        "entryTime": "2026-02-15T15:03:44.246Z",
        "status": "CLOSED",
        "exitPrice": 0.5031,
        "exitTime": "2026-02-13T00:13:44.223Z",
        "exitReason": "PARTIAL_CLOSE",
        "pnl": 18.075422626788043,
        "pnlPercent": 9.037711313394022
      },
      {
        "id": 36,
        "signalId": 36,
        "marketId": "market-2",
        "marketName": "Test Market 2",
        "side": "YES",
        "entryPrice": 0.4813,
        "entryDeviation": 0.03510000000000002,
        "amount": 200,
        "quantity": 415.541242468315,
        "entryTime": "2026-02-15T15:03:44.248Z",
        "status": "CLOSED",
        "exitPrice": 0.5035,
        "exitTime": "2026-02-14T00:08:44.221Z",
        "exitReason": "PARTIAL_CLOSE",
        "pnl": 9.22501558279657,
        "pnlPercent": 4.612507791398285
      },
      {
        "id": 37,
        "signalId": 37,
        "marketId": "market-3",
        "marketName": "Test Market 3",
        "side": "NO",
        "entryPrice": 0.4817,
        "entryDeviation": 0.033399999999999985,
        "amount": 200,
        "quantity": 415.1961801951422,
        "entryTime": "2026-02-15T15:03:44.248Z",
        "status": "CLOSED",
        "exitPrice": 0.4965,
        "exitTime": "2026-02-14T00:13:44.222Z",
        "exitReason": "PARTIAL_CLOSE",
        "pnl": 6.1449034668880955,
        "pnlPercent": 3.0724517334440478
      },
      {
        "id": 38,
        "signalId": 38,
        "marketId": "market-4",
        "marketName": "Test Market 4",
        "side": "NO",
        "entryPrice": 0.4818,
        "entryDeviation": 0.03600000000000003,
        "amount": 200,
        "quantity": 415.11000415110004,
        "entryTime": "2026-02-15T15:03:44.248Z",
        "status": "CLOSED",
        "exitPrice": 0.497,
        "exitTime": "2026-02-14T00:08:44.223Z",
        "exitReason": "PARTIAL_CLOSE",
        "pnl": 6.309672063096717,
        "pnlPercent": 3.154836031548359
      },
      {
        "id": 39,
        "signalId": 39,
        "marketId": "market-3",
        "marketName": "Test Market 3",
        "side": "YES",
        "entryPrice": 0.4795,
        "entryDeviation": 0.037800000000000056,
        "amount": 200,
        "quantity": 417.10114702815434,
        "entryTime": "2026-02-15T15:03:44.248Z",
        "status": "CLOSED",
        "exitPrice": 0.4984,
        "exitTime": "2026-02-14T00:13:44.222Z",
        "exitReason": "PARTIAL_CLOSE",
        "pnl": 7.8832116788321285,
        "pnlPercent": 3.9416058394160647
      },
      {
        "id": 40,
        "signalId": 40,
        "marketId": "market-2",
        "marketName": "Test Market 2",
        "side": "YES",
        "entryPrice": 0.4731,
        "entryDeviation": 0.047699999999999965,
        "amount": 200,
        "quantity": 422.7436060029592,
        "entryTime": "2026-02-15T15:03:44.248Z",
        "status": "CLOSED",
        "exitPrice": 0.4978,
        "exitTime": "2026-02-14T00:18:44.221Z",
        "exitReason": "PARTIAL_CLOSE",
        "pnl": 10.441767068273093,
        "pnlPercent": 5.220883534136546
      },
      {
        "id": 41,
        "signalId": 41,
        "marketId": "market-4",
        "marketName": "Test Market 4",
        "side": "NO",
        "entryPrice": 0.4588,
        "entryDeviation": 0.07730000000000004,
        "amount": 200,
        "quantity": 435.9197907585004,
        "entryTime": "2026-02-15T15:03:44.251Z",
        "status": "CLOSED",
        "exitPrice": 0.5023,
        "exitTime": "2026-02-15T00:08:44.223Z",
        "exitReason": "PARTIAL_CLOSE",
        "pnl": 18.96251089799476,
        "pnlPercent": 9.48125544899738
      },
      {
        "id": 42,
        "signalId": 42,
        "marketId": "market-5",
        "marketName": "Test Market 5",
        "side": "YES",
        "entryPrice": 0.4683,
        "entryDeviation": 0.05699999999999994,
        "amount": 200,
        "quantity": 427.07666026051675,
        "entryTime": "2026-02-15T15:03:44.251Z",
        "status": "CLOSED",
        "exitPrice": 0.5042,
        "exitTime": "2026-02-15T00:13:44.224Z",
        "exitReason": "PARTIAL_CLOSE",
        "pnl": 15.332052103352545,
        "pnlPercent": 7.666026051676273
      },
      {
        "id": 43,
        "signalId": 43,
        "marketId": "market-1",
        "marketName": "Test Market 1",
        "side": "YES",
        "entryPrice": 0.4637,
        "entryDeviation": 0.06730000000000003,
        "amount": 200,
        "quantity": 431.31334914815614,
        "entryTime": "2026-02-15T15:03:44.251Z",
        "status": "CLOSED",
        "exitPrice": 0.5012,
        "exitTime": "2026-02-15T00:18:44.219Z",
        "exitReason": "PARTIAL_CLOSE",
        "pnl": 16.174250593055845,
        "pnlPercent": 8.087125296527923
      },
      {
        "id": 44,
        "signalId": 44,
        "marketId": "market-3",
        "marketName": "Test Market 3",
        "side": "NO",
        "entryPrice": 0.4758,
        "entryDeviation": 0.046599999999999975,
        "amount": 200,
        "quantity": 420.3446826397646,
        "entryTime": "2026-02-15T15:03:44.251Z",
        "status": "CLOSED",
        "exitPrice": 0.5026,
        "exitTime": "2026-02-15T00:28:44.222Z",
        "exitReason": "PARTIAL_CLOSE",
        "pnl": 11.26523749474571,
        "pnlPercent": 5.632618747372855
      },
      {
        "id": 45,
        "signalId": 45,
        "marketId": "market-4",
        "marketName": "Test Market 4",
        "side": "YES",
        "entryPrice": 0.4761,
        "entryDeviation": 0.0413,
        "amount": 200,
        "quantity": 420.0798151648813,
        "entryTime": "2026-02-15T15:03:44.251Z",
        "status": "CLOSED",
        "exitPrice": 0.4998,
        "exitTime": "2026-02-15T00:23:44.223Z",
        "exitReason": "PARTIAL_CLOSE",
        "pnl": 9.955891619407687,
        "pnlPercent": 4.977945809703844
      }
    ]
  }
}